Metadata-Version: 1.0
Name: mleng-distributions
Version: 0.1
Summary: Gaussian & Binomial distributions
Home-page: UNKNOWN
Author: Adrian R
Author-email: UNKNOWN
License: UNKNOWN
Platform: UNKNOWN
